deltadask/__init__.py
deltadask-0.2.0.dist-info/METADATA
deltadask-0.2.0.dist-info/WHEEL
deltadask-0.2.0.dist-info/RECORD
