Metadata-Version: 2.1
Name: deltadask
Version: 0.2.0
Summary: 
Author: Matthew Powers
Author-email: matthewkevinpowers@gmail.com
Requires-Python: >=3.9,<4.0
Classifier: Programming Language :: Python :: 3
Classifier: Programming Language :: Python :: 3.9
Classifier: Programming Language :: Python :: 3.10
Classifier: Programming Language :: Python :: 3.11
Requires-Dist: dask (>=2022.10.2,<2023.0.0)
Requires-Dist: deltalake (>=0.8.1,<0.9.0)
Requires-Dist: pandas (>=1.5.3,<2.0.0)
